<?xml version="1.0" encoding="UTF-8"?>
<objects serializationModel="Studio.01.10.00">
    <object class="AudioFile" id="{d7531e92-2281-4eb3-8213-6222a35a26e9}">
        <property name="assetPath">
            <value>soundclips/sm/entermerge.wav</value>
        </property>
        <property name="frequencyInKHz">
            <value>44.0999985</value>
        </property>
        <property name="channelCount">
            <value>1</value>
        </property>
        <property name="length">
            <value>1.1609977324263039</value>
        </property>
        <relationship name="masterAssetFolder">
            <destination>{7934f37e-95bd-414b-beb2-417a7b01c5d0}</destination>
        </relationship>
    </object>
</objects>
