[
  {
    "name": "btUp",
    "all": false,
    "buttons": [ "w", "pad_lanalogy" , "pad_up"]
  },
  {
    "name": "btDown",
    "all": false,
    "buttons": [ "s", "pad_down" ]
  },
  {
    "name": "btRight",
    "all": false,
    "buttons": [ "d", "pad_lanalogx" ]
  },
  {
    "name": "btLeft",
    "all": false,
    "buttons": [ "a" ]
  },
  {
    "name": "btShadowMerging",
    "all": false,
    "buttons": [ "mouse_right", "pad_r2" ]
  },
  {
    "name": "btAttack",
    "all": false,
    "buttons": [ "mouse_left", "pad_x" ]
  },
  {
    "name": "btRun",
    "all": false,
    "buttons": [ "shift", "pad_l2" ]
  },
  {
    "name": "MouseX",
    "all": false,
    "buttons": [ "pad_ranalogx" ]
  },
  {
    "name": "MouseY",
    "all": false,
    "buttons": [ "pad_ranalogy" ]
  },
  {
    "name": "Horizontal",
    "all": false,
    "buttons": [ "a", "d", "pad_lanalogx" ]
  },
  {
    "name": "Vertical",
    "all": false,
    "buttons": [ "w", "s", "pad_lanalogy" ]
  },
  {
    "name": "btAction",
    "all": false,
    "buttons": [ "e", "pad_a" ]
  },
  {
    "name": "btCrouch",
    "all": false,
    "buttons": [ "c", "pad_b" ]
  },
  {
    "name": "btSecAction",
    "all": false,
    "buttons":  ["space", "pad_y"]
  },
  {
	"name": "btSonar",
	"all": false,
	"buttons": ["q", "pad_r3"]
  },
  {
    "name": "btDebugPause",
    "all": false,
    "buttons":  ["f1"]
  },
  {
    "name": "btDebugShadows",
    "all": false,
    "buttons":  ["f2"]
  },
	{
    "name": "btDebugMode",
    "all": false,
    "buttons":  ["f3"]
  },
	{
    "name": "btDebugParticles",
    "all": false,
    "buttons":  ["f4"]
  },
	{
    "name": "btDebugModeUnpaused",
    "all": false,
    "buttons":  ["f5"]
  },
  {
    "name": "btPause",
    "all": false,
    "buttons":  ["escape", "pad_start"]
  },
  {
    "name": "btUpAux",
    "all": false,
    "buttons":  ["pad_up", "up"]
  },
  {
    "name": "btDownAux",
    "all": false,
    "buttons":  ["pad_down", "down"]
  },
  {
    "name": "btMenuConfirm",
    "all": false,
    "buttons":  ["return", "pad_a"]
  },
  {
    "name": "btMenuCancel",
    "all": false,
    "buttons":  ["pad_b"]
  },
  {
	"name": "btConsole",
	"all": false,
	"buttons": ["oem_4"]
  },
  {
    "name": "btMouseRClick",
    "all": false,
    "buttons": [ "mouse_right" ]
  },
  {
    "name": "btMouseLClick",
    "all": false,
    "buttons": [ "mouse_left" ]
  },
  {
    "name": "btR_btMouseRClick",
    "all": true,
    "buttons": [ "r", "mouse_right" ]
  },
  {
    "name": "btR_btMouseLClick",
    "all": true,
    "buttons": [ "r", "mouse_left" ]
  }
]